LICENSE
MANIFEST.in
README.rst
setup.py
tdlib.py
tdlib.egg-info/PKG-INFO
tdlib.egg-info/SOURCES.txt
tdlib.egg-info/dependency_links.txt
tdlib.egg-info/top_level.txt