Metadata-Version: 1.0
Name: tdlib
Version: 0.0.1
Summary: A cross-platform library for building Telegram clients (Python wrapper)
Home-page: https://github.com/tdlib/td
Author: Alexander Pushkov
Author-email: UNKNOWN
License: UNKNOWN
Platform: UNKNOWN
